odoo8_addon_l10n_es_pos-8.0.1.0.0.99.dev15-py3.6-nspkg.pth
odoo_addons/l10n_es_pos/README.rst
odoo_addons/l10n_es_pos/__init__.py
odoo_addons/l10n_es_pos/__openerp__.py
odoo_addons/l10n_es_pos/i18n/bg.po
odoo_addons/l10n_es_pos/i18n/ca.po
odoo_addons/l10n_es_pos/i18n/cs.po
odoo_addons/l10n_es_pos/i18n/en_US.po
odoo_addons/l10n_es_pos/i18n/es.po
odoo_addons/l10n_es_pos/i18n/es_CR.po
odoo_addons/l10n_es_pos/i18n/fr.po
odoo_addons/l10n_es_pos/i18n/gl.po
odoo_addons/l10n_es_pos/i18n/hr.po
odoo_addons/l10n_es_pos/i18n/l10n_es_pos.pot
odoo_addons/l10n_es_pos/i18n/nl.po
odoo_addons/l10n_es_pos/i18n/pl.po
odoo_addons/l10n_es_pos/i18n/pt.po
odoo_addons/l10n_es_pos/i18n/pt_BR.po
odoo_addons/l10n_es_pos/i18n/ru.po
odoo_addons/l10n_es_pos/i18n/sl.po
odoo_addons/l10n_es_pos/i18n/sv.po
odoo_addons/l10n_es_pos/i18n/tr.po
odoo_addons/l10n_es_pos/models/__init__.py
odoo_addons/l10n_es_pos/models/pos_config.py
odoo_addons/l10n_es_pos/models/pos_order.py
odoo_addons/l10n_es_pos/reports/common.xml
odoo_addons/l10n_es_pos/reports/receipt_report.xml
odoo_addons/l10n_es_pos/static/description/icon.png
odoo_addons/l10n_es_pos/static/src/css/pos.css
odoo_addons/l10n_es_pos/static/src/css/report.css
odoo_addons/l10n_es_pos/static/src/js/main.js
odoo_addons/l10n_es_pos/static/src/xml/pos.xml
odoo_addons/l10n_es_pos/views/point_of_sale_report.xml
odoo_addons/l10n_es_pos/views/point_of_sale_view.xml
odoo_addons/l10n_es_pos/views/pos_template.xml
odoo8_addon_l10n_es_pos-8.0.1.0.0.99.dev15.dist-info/METADATA
odoo8_addon_l10n_es_pos-8.0.1.0.0.99.dev15.dist-info/WHEEL
odoo8_addon_l10n_es_pos-8.0.1.0.0.99.dev15.dist-info/namespace_packages.txt
odoo8_addon_l10n_es_pos-8.0.1.0.0.99.dev15.dist-info/top_level.txt
odoo8_addon_l10n_es_pos-8.0.1.0.0.99.dev15.dist-info/RECORD
